rasa_contrib/__init__.py
rasa_contrib/core/__init__.py
rasa_contrib/core/policies/__init__.py
rasa_contrib/core/policies/stacked_bilstm_paddle_policy.py
rasa_contrib/core/policies/stacked_bilstm_tf_policy.py
rasa_contrib/nlu/__init__.py
rasa_contrib/nlu/classifiers/__init__.py
rasa_contrib/nlu/classifiers/dense_network_tf_classifier.py
rasa_contrib/nlu/classifiers/text_cnn_paddle_classifier.py
rasa_contrib/nlu/classifiers/text_cnn_tf_classifier.py
rasa_contrib/nlu/debugger/__init__.py
rasa_contrib/nlu/debugger/hooks.py
rasa_contrib/nlu/debugger/tensorflow_debugger.py
rasa_contrib/nlu/extractors/__init__.py
rasa_contrib/nlu/extractors/bilstm_crf_paddle_entity_extractor.py
rasa_contrib/nlu/extractors/bilstm_crf_tf_entity_extractor.py
rasa_contrib/nlu/featurizers/__init__.py
rasa_contrib/nlu/featurizers/base_featurizer.py
rasa_contrib/nlu/featurizers/bert_base.py
rasa_contrib/nlu/featurizers/bert_char_featurizer.py
rasa_contrib/nlu/featurizers/bert_text_featurizer.py
rasa_contrib/nlu/tokenizers/__init__.py
rasa_contrib/nlu/tokenizers/micro_addons_tokenizer.py
rasa_contrib/nlu/utils/__init__.py
rasa_contrib/nlu/utils/paddle_utils.py
rasa_contrib/nlu/utils/tensorflow_utils.py
rasa_contrib/utils/__init__.py
rasa_contrib/utils/trainning.py
tests/__init__.py
rasa_contrib-0.3.1.dist-info/LICENSE
rasa_contrib-0.3.1.dist-info/METADATA
rasa_contrib-0.3.1.dist-info/WHEEL
rasa_contrib-0.3.1.dist-info/top_level.txt
rasa_contrib-0.3.1.dist-info/RECORD
