Metadata-Version: 2.1
Name: rasa-contrib
Version: 0.3.1
Summary: Addons for Rasa
Home-page: https://github.com/howl-anderson/rasa_contrib
Author: Xiaoquan Kong
Author-email: u1mail2me@gmail.com
License: Apache 2.0
Platform: UNKNOWN
Requires-Dist: rasa
Requires-Dist: paddlepaddle
Requires-Dist: seq2label
Requires-Dist: tensorflow
Requires-Dist: seq2annotation
Requires-Dist: MicroTokenizer
